rockerc/__init__.py
rockerc/aid.py
rockerc/cli_args.py
rockerc/completion.py
rockerc/completion_loader.py
rockerc/core.py
rockerc/dp.py
rockerc/renv.py
rockerc/renv_rockerc_template.yaml
rockerc/renvsc.py
rockerc/rockerc.py
rockerc/rockervsc.py
rockerc/completions/__init__.py
rockerc/completions/aid.bash
rockerc/completions/dp.bash
rockerc/completions/renv.bash
rockerc/completions/rockerc.bash
rockerc-0.18.0.dist-info/METADATA
rockerc-0.18.0.dist-info/WHEEL
rockerc-0.18.0.dist-info/entry_points.txt
rockerc-0.18.0.dist-info/licenses/LICENSE
rockerc-0.18.0.dist-info/RECORD
