Metadata-Version: 2.4
Name: rockerc
Version: 0.18.0
Summary: A tool to parse rockerc.yaml files and pass on the arguments onto rocker
Project-URL: Source, https://github.com/blooop/rockerc
Project-URL: Home, https://github.com/blooop/rockerc
Author-email: Austin Gregg-Smith <blooop@gmail.com>
License-Expression: MIT
License-File: LICENSE
Requires-Dist: deps-rocker>=0.23.1
Requires-Dist: iterfzf>=1.0.0
Requires-Dist: pyyaml>=5
Requires-Dist: rocker>=0.2.19
Provides-Extra: extensions
Requires-Dist: ghrocker==0.0.10; extra == 'extensions'
Requires-Dist: groot-rocker==0.4.1; extra == 'extensions'
Provides-Extra: test
Requires-Dist: coverage<=7.12.0,>=7.5.4; extra == 'test'
Requires-Dist: hypothesis<=6.148.3,>=6.104.2; extra == 'test'
Requires-Dist: pre-commit<=4.5.0; extra == 'test'
Requires-Dist: pylint<=4.0.3,>=3.2.5; extra == 'test'
Requires-Dist: pytest-cov<=7.0.0,>=4.1; extra == 'test'
Requires-Dist: pytest<=9.0.1,>=7.4; extra == 'test'
Requires-Dist: ruff<=0.14.7,>=0.5.0; extra == 'test'
